LICENSE
README.md
setup.py
wisconsin_covid19/__init__.py
wisconsin_covid19/api.py
wisconsin_covid19/exceptions.py
wisconsin_covid19/models.py
wisconsin_covid19.egg-info/PKG-INFO
wisconsin_covid19.egg-info/SOURCES.txt
wisconsin_covid19.egg-info/dependency_links.txt
wisconsin_covid19.egg-info/requires.txt
wisconsin_covid19.egg-info/top_level.txt