Metadata-Version: 2.1
Name: wisconsin-covid19
Version: 0.0.2
Summary: The Unofficial Wisconsin COVID API Wrapper in Python 3.
Home-page: https://github.com/davidteather/Wisconsin-Covid19-API
Author: David Teather
Author-email: contact.davidteather@gmail.com
License: MIT
Download-URL: https://github.com/davidteather/Wisconsin-Covid19-API/tarball/master
Keywords: wisconsin,covid19,covid-19
Platform: UNKNOWN
Classifier: Development Status :: 3 - Alpha
Classifier: Intended Audience :: Developers
Classifier: Topic :: Software Development :: Build Tools
Classifier: License :: OSI Approved :: MIT License
Classifier: Programming Language :: Python :: 3.6
Classifier: Programming Language :: Python :: 3.7
Classifier: Programming Language :: Python :: 3.8
Classifier: Programming Language :: Python :: 3.9
License-File: LICENSE
